{"frames":{"picto_vrilleo0.png":{"frame":{"x":0,"y":0,"w":278,"h":162},"rotated":false,"trimmed":false,"spriteSourceSize":{"x":0,"y":0,"w":278,"h":162},"sourceSize":{"w":278,"h":162}},"picto_vrilleo1.png":{"frame":{"x":278,"y":0,"w":278,"h":162},"rotated":false,"trimmed":false,"spriteSourceSize":{"x":0,"y":0,"w":278,"h":162},"sourceSize":{"w":278,"h":162}},"picto_vrilleo2.png":{"frame":{"x":556,"y":0,"w":278,"h":162},"rotated":false,"trimmed":false,"spriteSourceSize":{"x":0,"y":0,"w":278,"h":162},"sourceSize":{"w":278,"h":162}},"picto_vrilleo3.png":{"frame":{"x":834,"y":0,"w":278,"h":162},"rotated":false,"trimmed":false,"spriteSourceSize":{"x":0,"y":0,"w":278,"h":162},"sourceSize":{"w":278,"h":162}},"picto_vrilleo4.png":{"frame":{"x":1112,"y":0,"w":278,"h":162},"rotated":false,"trimmed":false,"spriteSourceSize":{"x":0,"y":0,"w":278,"h":162},"sourceSize":{"w":278,"h":162}},"picto_vrilleo5.png":{"frame":{"x":1390,"y":0,"w":278,"h":162},"rotated":false,"trimmed":false,"spriteSourceSize":{"x":0,"y":0,"w":278,"h":162},"sourceSize":{"w":278,"h":162}},"picto_vrilleo6.png":{"frame":{"x":1668,"y":0,"w":278,"h":162},"rotated":false,"trimmed":false,"spriteSourceSize":{"x":0,"y":0,"w":278,"h":162},"sourceSize":{"w":278,"h":162}},"picto_vrilleo7.png":{"frame":{"x":1946,"y":0,"w":278,"h":162},"rotated":false,"trimmed":false,"spriteSourceSize":{"x":0,"y":0,"w":278,"h":162},"sourceSize":{"w":278,"h":162}},"picto_vrilleo8.png":{"frame":{"x":0,"y":162,"w":278,"h":162},"rotated":false,"trimmed":false,"spriteSourceSize":{"x":0,"y":0,"w":278,"h":162},"sourceSize":{"w":278,"h":162}},"picto_vrilleo9.png":{"frame":{"x":278,"y":162,"w":278,"h":162},"rotated":false,"trimmed":false,"spriteSourceSize":{"x":0,"y":0,"w":278,"h":162},"sourceSize":{"w":278,"h":162}},"picto_vrilleo10.png":{"frame":{"x":556,"y":162,"w":278,"h":162},"rotated":false,"trimmed":false,"spriteSourceSize":{"x":0,"y":0,"w":278,"h":162},"sourceSize":{"w":278,"h":162}},"picto_vrilleo11.png":{"frame":{"x":834,"y":162,"w":278,"h":162},"rotated":false,"trimmed":false,"spriteSourceSize":{"x":0,"y":0,"w":278,"h":162},"sourceSize":{"w":278,"h":162}},"picto_vrilleo12.png":{"frame":{"x":1112,"y":162,"w":278,"h":162},"rotated":false,"trimmed":false,"spriteSourceSize":{"x":0,"y":0,"w":278,"h":162},"sourceSize":{"w":278,"h":162}},"picto_vrilleo13.png":{"frame":{"x":1390,"y":162,"w":278,"h":162},"rotated":false,"trimmed":false,"spriteSourceSize":{"x":0,"y":0,"w":278,"h":162},"sourceSize":{"w":278,"h":162}},"picto_vrilleo14.png":{"frame":{"x":1668,"y":162,"w":278,"h":162},"rotated":false,"trimmed":false,"spriteSourceSize":{"x":0,"y":0,"w":278,"h":162},"sourceSize":{"w":278,"h":162}},"picto_vrilleo15.png":{"frame":{"x":1946,"y":162,"w":278,"h":162},"rotated":false,"trimmed":false,"spriteSourceSize":{"x":0,"y":0,"w":278,"h":162},"sourceSize":{"w":278,"h":162}},"picto_vrilleo16.png":{"frame":{"x":0,"y":324,"w":278,"h":162},"rotated":false,"trimmed":false,"spriteSourceSize":{"x":0,"y":0,"w":278,"h":162},"sourceSize":{"w":278,"h":162}},"picto_vrilleo17.png":{"frame":{"x":278,"y":324,"w":278,"h":162},"rotated":false,"trimmed":false,"spriteSourceSize":{"x":0,"y":0,"w":278,"h":162},"sourceSize":{"w":278,"h":162}},"picto_vrilleo18.png":{"frame":{"x":556,"y":324,"w":278,"h":162},"rotated":false,"trimmed":false,"spriteSourceSize":{"x":0,"y":0,"w":278,"h":162},"sourceSize":{"w":278,"h":162}},"picto_vrilleo19.png":{"frame":{"x":834,"y":324,"w":278,"h":162},"rotated":false,"trimmed":false,"spriteSourceSize":{"x":0,"y":0,"w":278,"h":162},"sourceSize":{"w":278,"h":162}},"picto_vrilleo20.png":{"frame":{"x":1112,"y":324,"w":278,"h":162},"rotated":false,"trimmed":false,"spriteSourceSize":{"x":0,"y":0,"w":278,"h":162},"sourceSize":{"w":278,"h":162}},"picto_vrilleo21.png":{"frame":{"x":1390,"y":324,"w":278,"h":162},"rotated":false,"trimmed":false,"spriteSourceSize":{"x":0,"y":0,"w":278,"h":162},"sourceSize":{"w":278,"h":162}},"picto_vrilleo22.png":{"frame":{"x":1668,"y":324,"w":278,"h":162},"rotated":false,"trimmed":false,"spriteSourceSize":{"x":0,"y":0,"w":278,"h":162},"sourceSize":{"w":278,"h":162}},"picto_vrilleo23.png":{"frame":{"x":1946,"y":324,"w":278,"h":162},"rotated":false,"trimmed":false,"spriteSourceSize":{"x":0,"y":0,"w":278,"h":162},"sourceSize":{"w":278,"h":162}},"picto_vrilleo24.png":{"frame":{"x":0,"y":486,"w":278,"h":162},"rotated":false,"trimmed":false,"spriteSourceSize":{"x":0,"y":0,"w":278,"h":162},"sourceSize":{"w":278,"h":162}},"picto_vrilleo25.png":{"frame":{"x":278,"y":486,"w":278,"h":162},"rotated":false,"trimmed":false,"spriteSourceSize":{"x":0,"y":0,"w":278,"h":162},"sourceSize":{"w":278,"h":162}},"picto_vrilleo26.png":{"frame":{"x":556,"y":486,"w":278,"h":162},"rotated":false,"trimmed":false,"spriteSourceSize":{"x":0,"y":0,"w":278,"h":162},"sourceSize":{"w":278,"h":162}},"picto_vrilleo27.png":{"frame":{"x":834,"y":486,"w":278,"h":162},"rotated":false,"trimmed":false,"spriteSourceSize":{"x":0,"y":0,"w":278,"h":162},"sourceSize":{"w":278,"h":162}},"picto_vrilleo28.png":{"frame":{"x":1112,"y":486,"w":278,"h":162},"rotated":false,"trimmed":false,"spriteSourceSize":{"x":0,"y":0,"w":278,"h":162},"sourceSize":{"w":278,"h":162}},"picto_vrilleo29.png":{"frame":{"x":1390,"y":486,"w":278,"h":162},"rotated":false,"trimmed":false,"spriteSourceSize":{"x":0,"y":0,"w":278,"h":162},"sourceSize":{"w":278,"h":162}},"picto_vrilleo30.png":{"frame":{"x":1668,"y":486,"w":278,"h":162},"rotated":false,"trimmed":false,"spriteSourceSize":{"x":0,"y":0,"w":278,"h":162},"sourceSize":{"w":278,"h":162}},"picto_vrilleo31.png":{"frame":{"x":1946,"y":486,"w":278,"h":162},"rotated":false,"trimmed":false,"spriteSourceSize":{"x":0,"y":0,"w":278,"h":162},"sourceSize":{"w":278,"h":162}},"picto_vrilleo32.png":{"frame":{"x":0,"y":648,"w":278,"h":162},"rotated":false,"trimmed":false,"spriteSourceSize":{"x":0,"y":0,"w":278,"h":162},"sourceSize":{"w":278,"h":162}},"picto_vrilleo33.png":{"frame":{"x":278,"y":648,"w":278,"h":162},"rotated":false,"trimmed":false,"spriteSourceSize":{"x":0,"y":0,"w":278,"h":162},"sourceSize":{"w":278,"h":162}},"picto_vrilleo34.png":{"frame":{"x":556,"y":648,"w":278,"h":162},"rotated":false,"trimmed":false,"spriteSourceSize":{"x":0,"y":0,"w":278,"h":162},"sourceSize":{"w":278,"h":162}},"picto_vrilleo35.png":{"frame":{"x":834,"y":648,"w":278,"h":162},"rotated":false,"trimmed":false,"spriteSourceSize":{"x":0,"y":0,"w":278,"h":162},"sourceSize":{"w":278,"h":162}},"picto_vrilleo36.png":{"frame":{"x":1112,"y":648,"w":278,"h":162},"rotated":false,"trimmed":false,"spriteSourceSize":{"x":0,"y":0,"w":278,"h":162},"sourceSize":{"w":278,"h":162}},"picto_vrilleo37.png":{"frame":{"x":1390,"y":648,"w":278,"h":162},"rotated":false,"trimmed":false,"spriteSourceSize":{"x":0,"y":0,"w":278,"h":162},"sourceSize":{"w":278,"h":162}},"picto_vrilleo38.png":{"frame":{"x":1668,"y":648,"w":278,"h":162},"rotated":false,"trimmed":false,"spriteSourceSize":{"x":0,"y":0,"w":278,"h":162},"sourceSize":{"w":278,"h":162}},"picto_vrilleo39.png":{"frame":{"x":1946,"y":648,"w":278,"h":162},"rotated":false,"trimmed":false,"spriteSourceSize":{"x":0,"y":0,"w":278,"h":162},"sourceSize":{"w":278,"h":162}},"picto_vrilleo40.png":{"frame":{"x":0,"y":810,"w":278,"h":162},"rotated":false,"trimmed":false,"spriteSourceSize":{"x":0,"y":0,"w":278,"h":162},"sourceSize":{"w":278,"h":162}},"picto_vrilleo41.png":{"frame":{"x":278,"y":810,"w":278,"h":162},"rotated":false,"trimmed":false,"spriteSourceSize":{"x":0,"y":0,"w":278,"h":162},"sourceSize":{"w":278,"h":162}},"picto_vrilleo42.png":{"frame":{"x":556,"y":810,"w":278,"h":162},"rotated":false,"trimmed":false,"spriteSourceSize":{"x":0,"y":0,"w":278,"h":162},"sourceSize":{"w":278,"h":162}},"picto_vrilleo43.png":{"frame":{"x":834,"y":810,"w":278,"h":162},"rotated":false,"trimmed":false,"spriteSourceSize":{"x":0,"y":0,"w":278,"h":162},"sourceSize":{"w":278,"h":162}},"picto_vrilleo44.png":{"frame":{"x":1112,"y":810,"w":278,"h":162},"rotated":false,"trimmed":false,"spriteSourceSize":{"x":0,"y":0,"w":278,"h":162},"sourceSize":{"w":278,"h":162}},"picto_vrilleo45.png":{"frame":{"x":1390,"y":810,"w":278,"h":162},"rotated":false,"trimmed":false,"spriteSourceSize":{"x":0,"y":0,"w":278,"h":162},"sourceSize":{"w":278,"h":162}},"picto_vrilleo46.png":{"frame":{"x":1668,"y":810,"w":278,"h":162},"rotated":false,"trimmed":false,"spriteSourceSize":{"x":0,"y":0,"w":278,"h":162},"sourceSize":{"w":278,"h":162}},"picto_vrilleo47.png":{"frame":{"x":1946,"y":810,"w":278,"h":162},"rotated":false,"trimmed":false,"spriteSourceSize":{"x":0,"y":0,"w":278,"h":162},"sourceSize":{"w":278,"h":162}},"picto_vrilleo48.png":{"frame":{"x":0,"y":972,"w":278,"h":162},"rotated":false,"trimmed":false,"spriteSourceSize":{"x":0,"y":0,"w":278,"h":162},"sourceSize":{"w":278,"h":162}},"picto_vrilleo49.png":{"frame":{"x":278,"y":972,"w":278,"h":162},"rotated":false,"trimmed":false,"spriteSourceSize":{"x":0,"y":0,"w":278,"h":162},"sourceSize":{"w":278,"h":162}},"picto_vrilleo50.png":{"frame":{"x":556,"y":972,"w":278,"h":162},"rotated":false,"trimmed":false,"spriteSourceSize":{"x":0,"y":0,"w":278,"h":162},"sourceSize":{"w":278,"h":162}},"picto_vrilleo51.png":{"frame":{"x":834,"y":972,"w":278,"h":162},"rotated":false,"trimmed":false,"spriteSourceSize":{"x":0,"y":0,"w":278,"h":162},"sourceSize":{"w":278,"h":162}},"picto_vrilleo52.png":{"frame":{"x":1112,"y":972,"w":278,"h":162},"rotated":false,"trimmed":false,"spriteSourceSize":{"x":0,"y":0,"w":278,"h":162},"sourceSize":{"w":278,"h":162}},"picto_vrilleo53.png":{"frame":{"x":1390,"y":972,"w":278,"h":162},"rotated":false,"trimmed":false,"spriteSourceSize":{"x":0,"y":0,"w":278,"h":162},"sourceSize":{"w":278,"h":162}},"picto_vrilleo54.png":{"frame":{"x":1668,"y":972,"w":278,"h":162},"rotated":false,"trimmed":false,"spriteSourceSize":{"x":0,"y":0,"w":278,"h":162},"sourceSize":{"w":278,"h":162}},"picto_vrilleo55.png":{"frame":{"x":1946,"y":972,"w":278,"h":162},"rotated":false,"trimmed":false,"spriteSourceSize":{"x":0,"y":0,"w":278,"h":162},"sourceSize":{"w":278,"h":162}},"picto_vrilleo56.png":{"frame":{"x":0,"y":1134,"w":278,"h":162},"rotated":false,"trimmed":false,"spriteSourceSize":{"x":0,"y":0,"w":278,"h":162},"sourceSize":{"w":278,"h":162}},"picto_vrilleo57.png":{"frame":{"x":278,"y":1134,"w":278,"h":162},"rotated":false,"trimmed":false,"spriteSourceSize":{"x":0,"y":0,"w":278,"h":162},"sourceSize":{"w":278,"h":162}},"picto_vrilleo58.png":{"frame":{"x":556,"y":1134,"w":278,"h":162},"rotated":false,"trimmed":false,"spriteSourceSize":{"x":0,"y":0,"w":278,"h":162},"sourceSize":{"w":278,"h":162}},"picto_vrilleo59.png":{"frame":{"x":834,"y":1134,"w":278,"h":162},"rotated":false,"trimmed":false,"spriteSourceSize":{"x":0,"y":0,"w":278,"h":162},"sourceSize":{"w":278,"h":162}},"picto_vrilleo60.png":{"frame":{"x":1112,"y":1134,"w":278,"h":162},"rotated":false,"trimmed":false,"spriteSourceSize":{"x":0,"y":0,"w":278,"h":162},"sourceSize":{"w":278,"h":162}},"picto_vrilleo61.png":{"frame":{"x":1390,"y":1134,"w":278,"h":162},"rotated":false,"trimmed":false,"spriteSourceSize":{"x":0,"y":0,"w":278,"h":162},"sourceSize":{"w":278,"h":162}},"picto_vrilleo62.png":{"frame":{"x":1668,"y":1134,"w":278,"h":162},"rotated":false,"trimmed":false,"spriteSourceSize":{"x":0,"y":0,"w":278,"h":162},"sourceSize":{"w":278,"h":162}},"picto_vrilleo63.png":{"frame":{"x":1946,"y":1134,"w":278,"h":162},"rotated":false,"trimmed":false,"spriteSourceSize":{"x":0,"y":0,"w":278,"h":162},"sourceSize":{"w":278,"h":162}},"picto_vrilleo64.png":{"frame":{"x":0,"y":1296,"w":278,"h":162},"rotated":false,"trimmed":false,"spriteSourceSize":{"x":0,"y":0,"w":278,"h":162},"sourceSize":{"w":278,"h":162}},"picto_vrilleo65.png":{"frame":{"x":278,"y":1296,"w":278,"h":162},"rotated":false,"trimmed":false,"spriteSourceSize":{"x":0,"y":0,"w":278,"h":162},"sourceSize":{"w":278,"h":162}},"picto_vrilleo66.png":{"frame":{"x":556,"y":1296,"w":278,"h":162},"rotated":false,"trimmed":false,"spriteSourceSize":{"x":0,"y":0,"w":278,"h":162},"sourceSize":{"w":278,"h":162}},"picto_vrilleo67.png":{"frame":{"x":834,"y":1296,"w":278,"h":162},"rotated":false,"trimmed":false,"spriteSourceSize":{"x":0,"y":0,"w":278,"h":162},"sourceSize":{"w":278,"h":162}},"picto_vrilleo68.png":{"frame":{"x":1112,"y":1296,"w":278,"h":162},"rotated":false,"trimmed":false,"spriteSourceSize":{"x":0,"y":0,"w":278,"h":162},"sourceSize":{"w":278,"h":162}},"picto_vrilleo69.png":{"frame":{"x":1390,"y":1296,"w":278,"h":162},"rotated":false,"trimmed":false,"spriteSourceSize":{"x":0,"y":0,"w":278,"h":162},"sourceSize":{"w":278,"h":162}},"picto_vrilleo70.png":{"frame":{"x":1668,"y":1296,"w":278,"h":162},"rotated":false,"trimmed":false,"spriteSourceSize":{"x":0,"y":0,"w":278,"h":162},"sourceSize":{"w":278,"h":162}},"picto_vrilleo71.png":{"frame":{"x":1946,"y":1296,"w":278,"h":162},"rotated":false,"trimmed":false,"spriteSourceSize":{"x":0,"y":0,"w":278,"h":162},"sourceSize":{"w":278,"h":162}},"picto_vrilleo72.png":{"frame":{"x":0,"y":1458,"w":278,"h":162},"rotated":false,"trimmed":false,"spriteSourceSize":{"x":0,"y":0,"w":278,"h":162},"sourceSize":{"w":278,"h":162}},"picto_vrilleo73.png":{"frame":{"x":278,"y":1458,"w":278,"h":162},"rotated":false,"trimmed":false,"spriteSourceSize":{"x":0,"y":0,"w":278,"h":162},"sourceSize":{"w":278,"h":162}},"picto_vrilleo74.png":{"frame":{"x":556,"y":1458,"w":278,"h":162},"rotated":false,"trimmed":false,"spriteSourceSize":{"x":0,"y":0,"w":278,"h":162},"sourceSize":{"w":278,"h":162}},"picto_vrilleo75.png":{"frame":{"x":834,"y":1458,"w":278,"h":162},"rotated":false,"trimmed":false,"spriteSourceSize":{"x":0,"y":0,"w":278,"h":162},"sourceSize":{"w":278,"h":162}},"picto_vrilleo76.png":{"frame":{"x":1112,"y":1458,"w":278,"h":162},"rotated":false,"trimmed":false,"spriteSourceSize":{"x":0,"y":0,"w":278,"h":162},"sourceSize":{"w":278,"h":162}},"picto_vrilleo77.png":{"frame":{"x":1390,"y":1458,"w":278,"h":162},"rotated":false,"trimmed":false,"spriteSourceSize":{"x":0,"y":0,"w":278,"h":162},"sourceSize":{"w":278,"h":162}},"picto_vrilleo78.png":{"frame":{"x":1668,"y":1458,"w":278,"h":162},"rotated":false,"trimmed":false,"spriteSourceSize":{"x":0,"y":0,"w":278,"h":162},"sourceSize":{"w":278,"h":162}},"picto_vrilleo79.png":{"frame":{"x":1946,"y":1458,"w":278,"h":162},"rotated":false,"trimmed":false,"spriteSourceSize":{"x":0,"y":0,"w":278,"h":162},"sourceSize":{"w":278,"h":162}},"picto_vrilleo80.png":{"frame":{"x":0,"y":1620,"w":278,"h":162},"rotated":false,"trimmed":false,"spriteSourceSize":{"x":0,"y":0,"w":278,"h":162},"sourceSize":{"w":278,"h":162}},"picto_vrilleo81.png":{"frame":{"x":278,"y":1620,"w":278,"h":162},"rotated":false,"trimmed":false,"spriteSourceSize":{"x":0,"y":0,"w":278,"h":162},"sourceSize":{"w":278,"h":162}},"picto_vrilleo82.png":{"frame":{"x":556,"y":1620,"w":278,"h":162},"rotated":false,"trimmed":false,"spriteSourceSize":{"x":0,"y":0,"w":278,"h":162},"sourceSize":{"w":278,"h":162}},"picto_vrilleo83.png":{"frame":{"x":834,"y":1620,"w":278,"h":162},"rotated":false,"trimmed":false,"spriteSourceSize":{"x":0,"y":0,"w":278,"h":162},"sourceSize":{"w":278,"h":162}},"picto_vrilleo84.png":{"frame":{"x":1112,"y":1620,"w":278,"h":162},"rotated":false,"trimmed":false,"spriteSourceSize":{"x":0,"y":0,"w":278,"h":162},"sourceSize":{"w":278,"h":162}},"picto_vrilleo85.png":{"frame":{"x":1390,"y":1620,"w":278,"h":162},"rotated":false,"trimmed":false,"spriteSourceSize":{"x":0,"y":0,"w":278,"h":162},"sourceSize":{"w":278,"h":162}},"picto_vrilleo86.png":{"frame":{"x":1668,"y":1620,"w":278,"h":162},"rotated":false,"trimmed":false,"spriteSourceSize":{"x":0,"y":0,"w":278,"h":162},"sourceSize":{"w":278,"h":162}},"picto_vrilleo87.png":{"frame":{"x":1946,"y":1620,"w":278,"h":162},"rotated":false,"trimmed":false,"spriteSourceSize":{"x":0,"y":0,"w":278,"h":162},"sourceSize":{"w":278,"h":162}},"picto_vrilleo88.png":{"frame":{"x":0,"y":1782,"w":278,"h":162},"rotated":false,"trimmed":false,"spriteSourceSize":{"x":0,"y":0,"w":278,"h":162},"sourceSize":{"w":278,"h":162}},"picto_vrilleo89.png":{"frame":{"x":278,"y":1782,"w":278,"h":162},"rotated":false,"trimmed":false,"spriteSourceSize":{"x":0,"y":0,"w":278,"h":162},"sourceSize":{"w":278,"h":162}},"picto_vrilleo90.png":{"frame":{"x":556,"y":1782,"w":278,"h":162},"rotated":false,"trimmed":false,"spriteSourceSize":{"x":0,"y":0,"w":278,"h":162},"sourceSize":{"w":278,"h":162}},"picto_vrilleo91.png":{"frame":{"x":834,"y":1782,"w":278,"h":162},"rotated":false,"trimmed":false,"spriteSourceSize":{"x":0,"y":0,"w":278,"h":162},"sourceSize":{"w":278,"h":162}},"picto_vrilleo92.png":{"frame":{"x":1112,"y":1782,"w":278,"h":162},"rotated":false,"trimmed":false,"spriteSourceSize":{"x":0,"y":0,"w":278,"h":162},"sourceSize":{"w":278,"h":162}},"picto_vrilleo93.png":{"frame":{"x":1390,"y":1782,"w":278,"h":162},"rotated":false,"trimmed":false,"spriteSourceSize":{"x":0,"y":0,"w":278,"h":162},"sourceSize":{"w":278,"h":162}},"picto_vrilleo94.png":{"frame":{"x":1668,"y":1782,"w":278,"h":162},"rotated":false,"trimmed":false,"spriteSourceSize":{"x":0,"y":0,"w":278,"h":162},"sourceSize":{"w":278,"h":162}},"picto_vrilleo95.png":{"frame":{"x":1946,"y":1782,"w":278,"h":162},"rotated":false,"trimmed":false,"spriteSourceSize":{"x":0,"y":0,"w":278,"h":162},"sourceSize":{"w":278,"h":162}},"picto_vrilleo96.png":{"frame":{"x":0,"y":1944,"w":278,"h":162},"rotated":false,"trimmed":false,"spriteSourceSize":{"x":0,"y":0,"w":278,"h":162},"sourceSize":{"w":278,"h":162}},"picto_vrilleo97.png":{"frame":{"x":278,"y":1944,"w":278,"h":162},"rotated":false,"trimmed":false,"spriteSourceSize":{"x":0,"y":0,"w":278,"h":162},"sourceSize":{"w":278,"h":162}},"picto_vrilleo98.png":{"frame":{"x":556,"y":1944,"w":278,"h":162},"rotated":false,"trimmed":false,"spriteSourceSize":{"x":0,"y":0,"w":278,"h":162},"sourceSize":{"w":278,"h":162}},"picto_vrilleo99.png":{"frame":{"x":834,"y":1944,"w":278,"h":162},"rotated":false,"trimmed":false,"spriteSourceSize":{"x":0,"y":0,"w":278,"h":162},"sourceSize":{"w":278,"h":162}},"picto_vrilleo100.png":{"frame":{"x":1112,"y":1944,"w":278,"h":162},"rotated":false,"trimmed":false,"spriteSourceSize":{"x":0,"y":0,"w":278,"h":162},"sourceSize":{"w":278,"h":162}},"picto_vrilleo101.png":{"frame":{"x":1390,"y":1944,"w":278,"h":162},"rotated":false,"trimmed":false,"spriteSourceSize":{"x":0,"y":0,"w":278,"h":162},"sourceSize":{"w":278,"h":162}},"picto_vrilleo102.png":{"frame":{"x":1668,"y":1944,"w":278,"h":162},"rotated":false,"trimmed":false,"spriteSourceSize":{"x":0,"y":0,"w":278,"h":162},"sourceSize":{"w":278,"h":162}}},"meta":{"app":"https://github.com/piskelapp/piskel/","version":"1.0","image":"picto_vrilleo.png","format":"RGBA8888","size":{"w":2224,"h":2106}}}